anchorscad_lib/test_tools/__init__.py
anchorscad_lib/test_tools/test_tools.py
anchorscad_test_tools-0.1.0.dist-info/METADATA
anchorscad_test_tools-0.1.0.dist-info/WHEEL
anchorscad_test_tools-0.1.0.dist-info/licenses/LICENSE
anchorscad_test_tools-0.1.0.dist-info/RECORD
