Metadata-Version: 2.4
Name: anchorscad-test-tools
Version: 0.1.0
Summary: Test helpers for Anchorscad packages.
Project-URL: Homepage, https://github.com/owebeeone/anchorscad-test-tools
Project-URL: Bug Tracker, https://github.com/owebeeone/anchorscad-test-tools/issues
Author-email: Gianni Mariani <gianni@mariani.ws>
License-File: LICENSE
Classifier: License :: OSI Approved :: GNU Lesser General Public License v2 or later (LGPLv2+)
Classifier: Operating System :: OS Independent
Classifier: Programming Language :: Python :: 3
Requires-Python: >=3.10
